base/__init__.py
base/asgi.py
base/settings.py
base/urls.py
base/wsgi.py
neural_admin/__init__.py
neural_admin/admin.py
neural_admin/apps.py
neural_admin/models.py
neural_admin/tests.py
neural_admin/views.py
neural_admin/migrations/__init__.py
neural_admin/static/js/listDisplay.js
neural_admin-1.1.3.dist-info/LICENSE
neural_admin-1.1.3.dist-info/METADATA
neural_admin-1.1.3.dist-info/WHEEL
neural_admin-1.1.3.dist-info/top_level.txt
neural_admin-1.1.3.dist-info/RECORD
