Metadata-Version: 2.1
Name: neural-admin
Version: 1.1.3
Author: Palusha
Maintainer: Palusha
Project-URL: Source Code, https://github.com/Palusha/NeuralDynamicsCustomAdmin
Classifier: Environment :: Web Environment
Classifier: Framework :: Django
Classifier: Intended Audience :: Developers
Classifier: License :: OSI Approved :: MIT License
Classifier: Operating System :: OS Independent
License-File: LICENSE
